phonechars/__init__.py
phonechars/__main__.py
phonechars/common.py
phonechars/copar.py
phonechars/ipa.py
phonechars/nexus.py
phonechars-0.1.dist-info/AUTHORS.md
phonechars-0.1.dist-info/LICENSE
phonechars-0.1.dist-info/METADATA
phonechars-0.1.dist-info/WHEEL
phonechars-0.1.dist-info/entry_points.txt
phonechars-0.1.dist-info/top_level.txt
phonechars-0.1.dist-info/RECORD
