Metadata-Version: 2.1
Name: phonechars
Version: 0.1
Summary: Extract phonological phylogenetic characters from aligned data
Home-page: https://github.com/tresoldi/phonechars
Author: Tiago Tresoldi
Author-email: tiago.tresoldi@lingfil.uu.se
License: MIT
Keywords: phonology,phylogenetics,alignment,language evolution
Classifier: License :: OSI Approved :: MIT License
Classifier: Operating System :: OS Independent
Classifier: Programming Language :: Python :: 3
Classifier: Topic :: Software Development :: Libraries
Requires-Python: >=3.6
License-File: LICENSE
License-File: AUTHORS.md
Requires-Dist: lingpy
Requires-Dist: lingrex
Requires-Dist: unidecode
Provides-Extra: dev
Requires-Dist: black ; extra == 'dev'
Requires-Dist: flake8 ; extra == 'dev'
Requires-Dist: twine ; extra == 'dev'
Requires-Dist: wheel ; extra == 'dev'
Requires-Dist: build ; extra == 'dev'
Provides-Extra: test
Requires-Dist: pytest ; extra == 'test'
